{
  "hash": "ad378066",
  "browserHash": "490c1f5b",
  "optimized": {
    "vue": {
      "src": "../../../node_modules/vue/dist/vue.runtime.esm-bundler.js",
      "file": "vue.js",
      "fileHash": "49952688",
      "needsInterop": false
    },
    "vitepress > @vue/devtools-api": {
      "src": "../../../node_modules/@vue/devtools-api/lib/esm/index.js",
      "file": "vitepress___@vue_devtools-api.js",
      "fileHash": "9e4f8e88",
      "needsInterop": false
    },
    "yl-ui-lib": {
      "src": "../../../node_modules/yl-ui-lib/dist/yl-ui.umd.js",
      "file": "yl-ui-lib.js",
      "fileHash": "5aef3a07",
      "needsInterop": true
    }
  },
  "chunks": {
    "chunk-NLG5GKHW": {
      "file": "chunk-NLG5GKHW.js"
    },
    "chunk-CF3WPAMV": {
      "file": "chunk-CF3WPAMV.js"
    }
  }
}